omshakya/__init__.py
omshakya/_bin_cc_or_sc/__init__.py
omshakya/_bin_cc_or_sc/__version__.py
omshakya/_bin_cc_or_sc/_jsonops.py
omshakya/_bin_cc_or_sc/_mongodbops.py
omshakya/_bin_cc_or_sc/_sqlops.py
omshakya/_bin_cc_or_sc/_traceprinter.py
omshakya/json/__init__.py
omshakya/json/json_utility.py
omshakya/mongo/__init__.py
omshakya/mongo/mongo_utility.py
omshakya/sql/__init__.py
omshakya/sql/sql_utility.py
omshakya-0.1.7.dist-info/LICENSE
omshakya-0.1.7.dist-info/METADATA
omshakya-0.1.7.dist-info/WHEEL
omshakya-0.1.7.dist-info/top_level.txt
omshakya-0.1.7.dist-info/RECORD
